fh_matui/__init__.py
fh_matui/_modidx.py
fh_matui/app_pages.py
fh_matui/components.py
fh_matui/core.py
fh_matui/datatable.py
fh_matui/foundations.py
fh_matui/web_pages.py
fh_matui-0.9.15.dist-info/licenses/LICENSE
fh_matui-0.9.15.dist-info/METADATA
fh_matui-0.9.15.dist-info/WHEEL
fh_matui-0.9.15.dist-info/entry_points.txt
fh_matui-0.9.15.dist-info/top_level.txt
fh_matui-0.9.15.dist-info/RECORD
